README.md
setup.py
ovos_skill_installer/__init__.py
ovos_skill_installer.egg-info/PKG-INFO
ovos_skill_installer.egg-info/SOURCES.txt
ovos_skill_installer.egg-info/dependency_links.txt
ovos_skill_installer.egg-info/requires.txt
ovos_skill_installer.egg-info/top_level.txt